b3Dv/__init__.py
b3Dv/camera.py
b3Dv/lights.py
b3Dv/materials.py
b3Dv/mesh.py
b3Dv/pointCloudNodes.py
b3Dv/scene.py
b3dv-2025.2.26.1.dist-info/METADATA
b3dv-2025.2.26.1.dist-info/WHEEL
b3dv-2025.2.26.1.dist-info/licenses/LICENSE.txt
b3dv-2025.2.26.1.dist-info/RECORD
