Metadata-Version: 2.4
Name: b3Dv
Version: 2025.2.26.1
Summary: A package to easily plot functions over 3D surfaces.
Project-URL: Homepage, https://github.com/ariva00/b3Dv
Project-URL: Repository, https://github.com/ariva00/b3Dv.git
Project-URL: Issues, https://github.com/ariva00/b3Dv/issues
Author: Alessandro Riva
License: MIT License
License-File: LICENSE.txt
Keywords: 3D,blender,functions,meshes,plotting,point clouds,surfaces,visualization
Classifier: Development Status :: 3 - Alpha
Classifier: Intended Audience :: Developers
Classifier: Intended Audience :: Science/Research
Classifier: License :: OSI Approved :: MIT License
Classifier: Programming Language :: Python :: 3
Classifier: Programming Language :: Python :: 3.10
Classifier: Programming Language :: Python :: 3.11
Requires-Python: >=3.10
Requires-Dist: bpy
Requires-Dist: numpy
Requires-Dist: open3d
Provides-Extra: docs
Requires-Dist: sphinx; extra == 'docs'
